gtfs2gmns/__init__.py
gtfs2gmns/gtfs2gmns.py
gtfs2gmns/utility_lib.py
gtfs2gmns/func_lib/__init__.py
gtfs2gmns/func_lib/data_convert.py
gtfs2gmns/func_lib/gen_node_link.py
gtfs2gmns/func_lib/generate_access_link.py
gtfs2gmns/func_lib/read_gtfs.py
gtfs2gmns-0.2.3.dist-info/LICENSE
gtfs2gmns-0.2.3.dist-info/METADATA
gtfs2gmns-0.2.3.dist-info/WHEEL
gtfs2gmns-0.2.3.dist-info/top_level.txt
gtfs2gmns-0.2.3.dist-info/RECORD
