Metadata-Version: 2.1
Name: gtfs2gmns
Version: 0.2.3
Summary: A class-based instance designed for reading, converting, analyzing, and visualizing GTFS data
Home-page: https://github.com/xyluo25/gtfs2gmns
Author: Xiangyong Luo, Fang Tang, Xuesong Simon Zhou
Author-email: Xiangyong Luo <luoxiangyong01@gmail.com>, Xuesong Simon Zhou <xzhou74@asu.com>, Fang Tang <fangt@asu.edu>
Maintainer-email: Xiangyong Luo <luoxiangyong01@gmail.com>
License: MIT License
Project-URL: Homepage, https://github.com/xyluo25/gtfs2gmns
Project-URL: Bug Tracker, https://github.com/xyluo25/gtfs2gmns/issues
Project-URL: License, https://github.com/xyluo25/gtfs2gmns/blob/main/LICENSE
Project-URL: Contact, https://github.com/xyluo25/gtfs2gmns
Project-URL: Download, https://www.pepy.tech/projects/gtfs2gmns
Keywords: General Transit Feed Specification (GTFS),GMNS,Visualization,Space-time Trajectory
Platform: all
Classifier: Programming Language :: Python :: 3
Classifier: Programming Language :: Python :: 3.10
Classifier: Programming Language :: Python :: 3.11
Classifier: Programming Language :: Python :: 3.12
Classifier: License :: OSI Approved :: MIT License
Classifier: Intended Audience :: Developers
Classifier: Operating System :: OS Independent
Classifier: Topic :: Software Development :: Libraries
Requires-Python: >=3.10
License-File: LICENSE
Requires-Dist: pandas ==2.2.2
Requires-Dist: pyufunc ==0.3.3
Requires-Dist: setuptools ==70.0.0
Requires-Dist: Shapely ==2.0.5
